{
    "version": "1.1.2",
    "architecture": {
        "64bit": {
            "url": "https://github.com/kupecloud/kupe-cli/releases/download/v1.1.2/kupe_1.1.2_windows_amd64.zip",
            "bin": [
                "kupe.exe"
            ],
            "hash": "b5b755e1b30595ebc6f3e02c7bf3ede5ca4bb7ba5573808b560c1a0670abd097"
        },
        "arm64": {
            "url": "https://github.com/kupecloud/kupe-cli/releases/download/v1.1.2/kupe_1.1.2_windows_arm64.zip",
            "bin": [
                "kupe.exe"
            ],
            "hash": "1f5c975a6cc96d34f9222f6a7950a398a2ce381a49cd3a369a258b072fa10011"
        }
    },
    "homepage": "https://kupe.cloud",
    "license": "Apache-2.0",
    "description": "Official CLI for Kupe Cloud"
}
